setup.py
mozmill_automation/__init__.py
mozmill_automation/application.py
mozmill_automation/errors.py
mozmill_automation/files.py
mozmill_automation/process.py
mozmill_automation/reports.py
mozmill_automation/repository.py
mozmill_automation/testrun.py
mozmill_automation.egg-info/PKG-INFO
mozmill_automation.egg-info/SOURCES.txt
mozmill_automation.egg-info/dependency_links.txt
mozmill_automation.egg-info/entry_points.txt
mozmill_automation.egg-info/not-zip-safe
mozmill_automation.egg-info/requires.txt
mozmill_automation.egg-info/top_level.txt