Metadata-Version: 1.1
Name: mozmill-automation
Version: 2.0.1
Summary: Automation scripts for Mozmill test execution
Home-page: https://github.com/mozilla/mozmill-automation
Author: Mozilla Automation and Tools team
Author-email: tools@lists.mozilla.org
License: MPL 2.0
Keywords: mozilla
Platform: UNKNOWN
Classifier: Environment :: Console
Classifier: Intended Audience :: Developers
Classifier: License :: OSI Approved :: Mozilla Public License 2.0 (MPL 2.0)
Classifier: Natural Language :: English
Classifier: Operating System :: OS Independent
Classifier: Programming Language :: Python
Classifier: Topic :: Software Development :: Libraries :: Python Modules
